[
    {
        "processed_items": 2000,
        "avg_error": 0.002145922746781116,
        "overestimation_percentage": 0.2145922746781116,
        "underestimation_percentage": 0.0,
        "exact_match_percentage": 99.78540772532189,
        "avg_query_time": 1.633167266845703e-06,
        "memory_usage": 48000.0,
        "load_factor": 0.2065,
        "percentiles": {
            "overestimation": {
                "50th": 1.0,
                "90th": 1.0,
                "95th": 1.0,
                "100th": 1.0
            },
            "underestimation": {
                "50th": 0.0,
                "90th": 0.0,
                "95th": 0.0,
                "100th": 0.0
            },
            "combined": {
                "50th": 1.0,
                "90th": 1.0,
                "95th": 1.0,
                "100th": 1.0
            }
        }
    },
    {
        "processed_items": 4000,
        "avg_error": 0.007471980074719801,
        "overestimation_percentage": 0.7471980074719801,
        "underestimation_percentage": 0.0,
        "exact_match_percentage": 99.25280199252802,
        "avg_query_time": 2.857208251953125e-06,
        "memory_usage": 48000.0,
        "load_factor": 0.332,
        "percentiles": {
            "overestimation": {
                "50th": 1.0,
                "90th": 1.0,
                "95th": 1.0,
                "100th": 1.0
            },
            "underestimation": {
                "50th": 0.0,
                "90th": 0.0,
                "95th": 0.0,
                "100th": 0.0
            },
            "combined": {
                "50th": 1.0,
                "90th": 1.0,
                "95th": 1.0,
                "100th": 1.0
            }
        }
    },
    {
        "processed_items": 6000,
        "avg_error": 0.01928374655647383,
        "overestimation_percentage": 1.7447199265381086,
        "underestimation_percentage": 0.0,
        "exact_match_percentage": 98.25528007346189,
        "avg_query_time": 3.5181045532226563e-06,
        "memory_usage": 48000.0,
        "load_factor": 0.428,
        "percentiles": {
            "overestimation": {
                "50th": 1.0,
                "90th": 1.0,
                "95th": 1.1999999999999957,
                "100th": 3.0
            },
            "underestimation": {
                "50th": 0.0,
                "90th": 0.0,
                "95th": 0.0,
                "100th": 0.0
            },
            "combined": {
                "50th": 1.0,
                "90th": 1.0,
                "95th": 1.1999999999999957,
                "100th": 3.0
            }
        }
    },
    {
        "processed_items": 8000,
        "avg_error": 0.03548153511947864,
        "overestimation_percentage": 3.403330919623461,
        "underestimation_percentage": 0.0,
        "exact_match_percentage": 96.59666908037654,
        "avg_query_time": 3.6342144012451173e-06,
        "memory_usage": 48000.0,
        "load_factor": 0.506,
        "percentiles": {
            "overestimation": {
                "50th": 1.0,
                "90th": 1.0,
                "95th": 1.0,
                "100th": 3.0
            },
            "underestimation": {
                "50th": 0.0,
                "90th": 0.0,
                "95th": 0.0,
                "100th": 0.0
            },
            "combined": {
                "50th": 1.0,
                "90th": 1.0,
                "95th": 1.0,
                "100th": 3.0
            }
        }
    },
    {
        "processed_items": 10000,
        "avg_error": 0.054087277197295634,
        "overestimation_percentage": 5.162876459741856,
        "underestimation_percentage": 0.0,
        "exact_match_percentage": 94.83712354025813,
        "avg_query_time": 3.692150115966797e-06,
        "memory_usage": 48000.0,
        "load_factor": 0.569,
        "percentiles": {
            "overestimation": {
                "50th": 1.0,
                "90th": 1.0,
                "95th": 1.0,
                "100th": 3.0
            },
            "underestimation": {
                "50th": 0.0,
                "90th": 0.0,
                "95th": 0.0,
                "100th": 0.0
            },
            "combined": {
                "50th": 1.0,
                "90th": 1.0,
                "95th": 1.0,
                "100th": 3.0
            }
        }
    },
    {
        "processed_items": 12000,
        "avg_error": 0.08227176220806794,
        "overestimation_percentage": 7.855626326963907,
        "underestimation_percentage": 0.0,
        "exact_match_percentage": 92.1443736730361,
        "avg_query_time": 3.5359859466552733e-06,
        "memory_usage": 48000.0,
        "load_factor": 0.6215,
        "percentiles": {
            "overestimation": {
                "50th": 1.0,
                "90th": 1.0,
                "95th": 1.0,
                "100th": 4.0
            },
            "underestimation": {
                "50th": 0.0,
                "90th": 0.0,
                "95th": 0.0,
                "100th": 0.0
            },
            "combined": {
                "50th": 1.0,
                "90th": 1.0,
                "95th": 1.0,
                "100th": 4.0
            }
        }
    },
    {
        "processed_items": 14000,
        "avg_error": 0.11569086651053864,
        "overestimation_percentage": 10.725995316159251,
        "underestimation_percentage": 0.0,
        "exact_match_percentage": 89.27400468384074,
        "avg_query_time": 3.6449432373046876e-06,
        "memory_usage": 48000.0,
        "load_factor": 0.6675,
        "percentiles": {
            "overestimation": {
                "50th": 1.0,
                "90th": 1.0,
                "95th": 2.0,
                "100th": 4.0
            },
            "underestimation": {
                "50th": 0.0,
                "90th": 0.0,
                "95th": 0.0,
                "100th": 0.0
            },
            "combined": {
                "50th": 1.0,
                "90th": 1.0,
                "95th": 2.0,
                "100th": 4.0
            }
        }
    },
    {
        "processed_items": 16000,
        "avg_error": 0.14449638759031025,
        "overestimation_percentage": 13.259668508287293,
        "underestimation_percentage": 0.0,
        "exact_match_percentage": 86.74033149171271,
        "avg_query_time": 3.5309791564941407e-06,
        "memory_usage": 48000.0,
        "load_factor": 0.703,
        "percentiles": {
            "overestimation": {
                "50th": 1.0,
                "90th": 1.0,
                "95th": 2.0,
                "100th": 5.0
            },
            "underestimation": {
                "50th": 0.0,
                "90th": 0.0,
                "95th": 0.0,
                "100th": 0.0
            },
            "combined": {
                "50th": 1.0,
                "90th": 1.0,
                "95th": 2.0,
                "100th": 5.0
            }
        }
    },
    {
        "processed_items": 18000,
        "avg_error": 0.1772250291488535,
        "overestimation_percentage": 15.701515740380877,
        "underestimation_percentage": 0.0,
        "exact_match_percentage": 84.29848425961912,
        "avg_query_time": 3.895998001098633e-06,
        "memory_usage": 48000.0,
        "load_factor": 0.7325,
        "percentiles": {
            "overestimation": {
                "50th": 1.0,
                "90th": 1.6999999999999886,
                "95th": 2.0,
                "100th": 6.0
            },
            "underestimation": {
                "50th": 0.0,
                "90th": 0.0,
                "95th": 0.0,
                "100th": 0.0
            },
            "combined": {
                "50th": 1.0,
                "90th": 1.6999999999999886,
                "95th": 2.0,
                "100th": 6.0
            }
        }
    },
    {
        "processed_items": 20000,
        "avg_error": 0.22475918658580094,
        "overestimation_percentage": 19.12236889047449,
        "underestimation_percentage": 0.0,
        "exact_match_percentage": 80.87763110952551,
        "avg_query_time": 3.7839412689208985e-06,
        "memory_usage": 48000.0,
        "load_factor": 0.763,
        "percentiles": {
            "overestimation": {
                "50th": 1.0,
                "90th": 1.0,
                "95th": 2.0,
                "100th": 17.0
            },
            "underestimation": {
                "50th": 0.0,
                "90th": 0.0,
                "95th": 0.0,
                "100th": 0.0
            },
            "combined": {
                "50th": 1.0,
                "90th": 1.0,
                "95th": 2.0,
                "100th": 17.0
            }
        }
    },
    {
        "processed_items": 22000,
        "avg_error": 0.26263297872340424,
        "overestimation_percentage": 22.14095744680851,
        "underestimation_percentage": 0.0,
        "exact_match_percentage": 77.8590425531915,
        "avg_query_time": 3.530025482177734e-06,
        "memory_usage": 48000.0,
        "load_factor": 0.7865,
        "percentiles": {
            "overestimation": {
                "50th": 1.0,
                "90th": 2.0,
                "95th": 2.0,
                "100th": 18.0
            },
            "underestimation": {
                "50th": 0.0,
                "90th": 0.0,
                "95th": 0.0,
                "100th": 0.0
            },
            "combined": {
                "50th": 1.0,
                "90th": 2.0,
                "95th": 2.0,
                "100th": 18.0
            }
        }
    },
    {
        "processed_items": 24000,
        "avg_error": 0.2963772642098688,
        "overestimation_percentage": 25.14053716427233,
        "underestimation_percentage": 0.0,
        "exact_match_percentage": 74.85946283572767,
        "avg_query_time": 3.566741943359375e-06,
        "memory_usage": 48000.0,
        "load_factor": 0.8065,
        "percentiles": {
            "overestimation": {
                "50th": 1.0,
                "90th": 2.0,
                "95th": 2.0,
                "100th": 21.0
            },
            "underestimation": {
                "50th": 0.0,
                "90th": 0.0,
                "95th": 0.0,
                "100th": 0.0
            },
            "combined": {
                "50th": 1.0,
                "90th": 2.0,
                "95th": 2.0,
                "100th": 21.0
            }
        }
    },
    {
        "processed_items": 26000,
        "avg_error": 0.3458823529411765,
        "overestimation_percentage": 28.941176470588236,
        "underestimation_percentage": 0.0,
        "exact_match_percentage": 71.05882352941177,
        "avg_query_time": 3.7009716033935546e-06,
        "memory_usage": 48000.0,
        "load_factor": 0.8215,
        "percentiles": {
            "overestimation": {
                "50th": 1.0,
                "90th": 2.0,
                "95th": 2.0,
                "100th": 25.0
            },
            "underestimation": {
                "50th": 0.0,
                "90th": 0.0,
                "95th": 0.0,
                "100th": 0.0
            },
            "combined": {
                "50th": 1.0,
                "90th": 2.0,
                "95th": 2.0,
                "100th": 25.0
            }
        }
    },
    {
        "processed_items": 28000,
        "avg_error": 0.3941565600882029,
        "overestimation_percentage": 32.60749724366042,
        "underestimation_percentage": 0.0,
        "exact_match_percentage": 67.39250275633958,
        "avg_query_time": 3.4368038177490232e-06,
        "memory_usage": 48000.0,
        "load_factor": 0.842,
        "percentiles": {
            "overestimation": {
                "50th": 1.0,
                "90th": 2.0,
                "95th": 2.0,
                "100th": 28.0
            },
            "underestimation": {
                "50th": 0.0,
                "90th": 0.0,
                "95th": 0.0,
                "100th": 0.0
            },
            "combined": {
                "50th": 1.0,
                "90th": 2.0,
                "95th": 2.0,
                "100th": 28.0
            }
        }
    },
    {
        "processed_items": 30000,
        "avg_error": 0.4515032679738562,
        "overestimation_percentage": 36.6797385620915,
        "underestimation_percentage": 0.0,
        "exact_match_percentage": 63.3202614379085,
        "avg_query_time": 3.704071044921875e-06,
        "memory_usage": 48000.0,
        "load_factor": 0.8565,
        "percentiles": {
            "overestimation": {
                "50th": 1.0,
                "90th": 2.0,
                "95th": 2.0,
                "100th": 28.0
            },
            "underestimation": {
                "50th": 0.0,
                "90th": 0.0,
                "95th": 0.0,
                "100th": 0.0
            },
            "combined": {
                "50th": 1.0,
                "90th": 2.0,
                "95th": 2.0,
                "100th": 28.0
            }
        }
    },
    {
        "processed_items": 32000,
        "avg_error": 0.49837621783662256,
        "overestimation_percentage": 39.54534099425431,
        "underestimation_percentage": 0.0,
        "exact_match_percentage": 60.45465900574569,
        "avg_query_time": 3.6649703979492187e-06,
        "memory_usage": 48000.0,
        "load_factor": 0.869,
        "percentiles": {
            "overestimation": {
                "50th": 1.0,
                "90th": 2.0,
                "95th": 2.0,
                "100th": 30.0
            },
            "underestimation": {
                "50th": 0.0,
                "90th": 0.0,
                "95th": 0.0,
                "100th": 0.0
            },
            "combined": {
                "50th": 1.0,
                "90th": 2.0,
                "95th": 2.0,
                "100th": 30.0
            }
        }
    },
    {
        "processed_items": 34000,
        "avg_error": 0.548926014319809,
        "overestimation_percentage": 42.81622911694511,
        "underestimation_percentage": 0.0,
        "exact_match_percentage": 57.1837708830549,
        "avg_query_time": 3.644227981567383e-06,
        "memory_usage": 48000.0,
        "load_factor": 0.8815,
        "percentiles": {
            "overestimation": {
                "50th": 1.0,
                "90th": 2.0,
                "95th": 2.0,
                "100th": 30.0
            },
            "underestimation": {
                "50th": 0.0,
                "90th": 0.0,
                "95th": 0.0,
                "100th": 0.0
            },
            "combined": {
                "50th": 1.0,
                "90th": 2.0,
                "95th": 2.0,
                "100th": 30.0
            }
        }
    },
    {
        "processed_items": 36000,
        "avg_error": 0.5934568748570122,
        "overestimation_percentage": 45.06977808281858,
        "underestimation_percentage": 0.0,
        "exact_match_percentage": 54.93022191718142,
        "avg_query_time": 3.542184829711914e-06,
        "memory_usage": 48000.0,
        "load_factor": 0.8935,
        "percentiles": {
            "overestimation": {
                "50th": 1.0,
                "90th": 2.0,
                "95th": 2.0,
                "100th": 31.0
            },
            "underestimation": {
                "50th": 0.0,
                "90th": 0.0,
                "95th": 0.0,
                "100th": 0.0
            },
            "combined": {
                "50th": 1.0,
                "90th": 2.0,
                "95th": 2.0,
                "100th": 31.0
            }
        }
    },
    {
        "processed_items": 38000,
        "avg_error": 0.6453590192644484,
        "overestimation_percentage": 48.204903677758324,
        "underestimation_percentage": 0.0,
        "exact_match_percentage": 51.79509632224168,
        "avg_query_time": 3.8077831268310547e-06,
        "memory_usage": 48000.0,
        "load_factor": 0.9045,
        "percentiles": {
            "overestimation": {
                "50th": 1.0,
                "90th": 2.0,
                "95th": 2.0,
                "100th": 32.0
            },
            "underestimation": {
                "50th": 0.0,
                "90th": 0.0,
                "95th": 0.0,
                "100th": 0.0
            },
            "combined": {
                "50th": 1.0,
                "90th": 2.0,
                "95th": 2.0,
                "100th": 32.0
            }
        }
    },
    {
        "processed_items": 40000,
        "avg_error": 0.6911857958148383,
        "overestimation_percentage": 51.06742760515747,
        "underestimation_percentage": 0.0,
        "exact_match_percentage": 48.93257239484253,
        "avg_query_time": 3.837108612060547e-06,
        "memory_usage": 48000.0,
        "load_factor": 0.912,
        "percentiles": {
            "overestimation": {
                "50th": 1.0,
                "90th": 2.0,
                "95th": 2.0,
                "100th": 33.0
            },
            "underestimation": {
                "50th": 0.0,
                "90th": 0.0,
                "95th": 0.0,
                "100th": 0.0
            },
            "combined": {
                "50th": 1.0,
                "90th": 2.0,
                "95th": 2.0,
                "100th": 33.0
            }
        }
    },
    {
        "processed_items": 42000,
        "avg_error": 0.7526838160826412,
        "overestimation_percentage": 54.283978124367025,
        "underestimation_percentage": 0.0,
        "exact_match_percentage": 45.716021875632975,
        "avg_query_time": 3.7598609924316405e-06,
        "memory_usage": 48000.0,
        "load_factor": 0.9215,
        "percentiles": {
            "overestimation": {
                "50th": 1.0,
                "90th": 2.0,
                "95th": 3.0,
                "100th": 34.0
            },
            "underestimation": {
                "50th": 0.0,
                "90th": 0.0,
                "95th": 0.0,
                "100th": 0.0
            },
            "combined": {
                "50th": 1.0,
                "90th": 2.0,
                "95th": 3.0,
                "100th": 34.0
            }
        }
    },
    {
        "processed_items": 44000,
        "avg_error": 0.8056751467710371,
        "overestimation_percentage": 57.04500978473581,
        "underestimation_percentage": 0.0,
        "exact_match_percentage": 42.95499021526419,
        "avg_query_time": 3.6568641662597654e-06,
        "memory_usage": 48000.0,
        "load_factor": 0.9275,
        "percentiles": {
            "overestimation": {
                "50th": 1.0,
                "90th": 2.0,
                "95th": 3.0,
                "100th": 34.0
            },
            "underestimation": {
                "50th": 0.0,
                "90th": 0.0,
                "95th": 0.0,
                "100th": 0.0
            },
            "combined": {
                "50th": 1.0,
                "90th": 2.0,
                "95th": 3.0,
                "100th": 34.0
            }
        }
    },
    {
        "processed_items": 46000,
        "avg_error": 0.8546555639666918,
        "overestimation_percentage": 59.67070401211204,
        "underestimation_percentage": 0.0,
        "exact_match_percentage": 40.32929598788797,
        "avg_query_time": 3.6211013793945314e-06,
        "memory_usage": 48000.0,
        "load_factor": 0.935,
        "percentiles": {
            "overestimation": {
                "50th": 1.0,
                "90th": 2.0,
                "95th": 3.0,
                "100th": 37.0
            },
            "underestimation": {
                "50th": 0.0,
                "90th": 0.0,
                "95th": 0.0,
                "100th": 0.0
            },
            "combined": {
                "50th": 1.0,
                "90th": 2.0,
                "95th": 3.0,
                "100th": 37.0
            }
        }
    },
    {
        "processed_items": 48000,
        "avg_error": 0.9147768836869057,
        "overestimation_percentage": 62.21653255303584,
        "underestimation_percentage": 0.0,
        "exact_match_percentage": 37.78346744696415,
        "avg_query_time": 3.5979747772216795e-06,
        "memory_usage": 48000.0,
        "load_factor": 0.938,
        "percentiles": {
            "overestimation": {
                "50th": 1.0,
                "90th": 2.0,
                "95th": 3.0,
                "100th": 39.0
            },
            "underestimation": {
                "50th": 0.0,
                "90th": 0.0,
                "95th": 0.0,
                "100th": 0.0
            },
            "combined": {
                "50th": 1.0,
                "90th": 2.0,
                "95th": 3.0,
                "100th": 39.0
            }
        }
    },
    {
        "processed_items": 50000,
        "avg_error": 0.9648499911237352,
        "overestimation_percentage": 64.40617788034795,
        "underestimation_percentage": 0.0,
        "exact_match_percentage": 35.59382211965205,
        "avg_query_time": 3.6721229553222654e-06,
        "memory_usage": 48000.0,
        "load_factor": 0.9425,
        "percentiles": {
            "overestimation": {
                "50th": 1.0,
                "90th": 2.0,
                "95th": 3.0,
                "100th": 39.0
            },
            "underestimation": {
                "50th": 0.0,
                "90th": 0.0,
                "95th": 0.0,
                "100th": 0.0
            },
            "combined": {
                "50th": 1.0,
                "90th": 2.0,
                "95th": 3.0,
                "100th": 39.0
            }
        }
    },
    {
        "processed_items": 52000,
        "avg_error": 1.0189753320683113,
        "overestimation_percentage": 66.01690529584268,
        "underestimation_percentage": 0.0,
        "exact_match_percentage": 33.983094704157324,
        "avg_query_time": 3.7829875946044924e-06,
        "memory_usage": 48000.0,
        "load_factor": 0.947,
        "percentiles": {
            "overestimation": {
                "50th": 1.0,
                "90th": 2.0,
                "95th": 3.0,
                "100th": 42.0
            },
            "underestimation": {
                "50th": 0.0,
                "90th": 0.0,
                "95th": 0.0,
                "100th": 0.0
            },
            "combined": {
                "50th": 1.0,
                "90th": 2.0,
                "95th": 3.0,
                "100th": 42.0
            }
        }
    },
    {
        "processed_items": 54000,
        "avg_error": 1.0712250712250713,
        "overestimation_percentage": 67.87330316742081,
        "underestimation_percentage": 0.0,
        "exact_match_percentage": 32.126696832579185,
        "avg_query_time": 3.6389827728271484e-06,
        "memory_usage": 48000.0,
        "load_factor": 0.9525,
        "percentiles": {
            "overestimation": {
                "50th": 1.0,
                "90th": 2.0,
                "95th": 3.0,
                "100th": 44.0
            },
            "underestimation": {
                "50th": 0.0,
                "90th": 0.0,
                "95th": 0.0,
                "100th": 0.0
            },
            "combined": {
                "50th": 1.0,
                "90th": 2.0,
                "95th": 3.0,
                "100th": 44.0
            }
        }
    },
    {
        "processed_items": 56000,
        "avg_error": 1.121266525216256,
        "overestimation_percentage": 69.29982046678636,
        "underestimation_percentage": 0.0,
        "exact_match_percentage": 30.700179533213646,
        "avg_query_time": 3.6127567291259767e-06,
        "memory_usage": 48000.0,
        "load_factor": 0.957,
        "percentiles": {
            "overestimation": {
                "50th": 1.0,
                "90th": 3.0,
                "95th": 3.0,
                "100th": 45.0
            },
            "underestimation": {
                "50th": 0.0,
                "90th": 0.0,
                "95th": 0.0,
                "100th": 0.0
            },
            "combined": {
                "50th": 1.0,
                "90th": 3.0,
                "95th": 3.0,
                "100th": 45.0
            }
        }
    },
    {
        "processed_items": 58000,
        "avg_error": 1.1814145258483983,
        "overestimation_percentage": 71.21788772597526,
        "underestimation_percentage": 0.0,
        "exact_match_percentage": 28.78211227402474,
        "avg_query_time": 3.5448074340820313e-06,
        "memory_usage": 48000.0,
        "load_factor": 0.9585,
        "percentiles": {
            "overestimation": {
                "50th": 1.0,
                "90th": 3.0,
                "95th": 3.0,
                "100th": 45.0
            },
            "underestimation": {
                "50th": 0.0,
                "90th": 0.0,
                "95th": 0.0,
                "100th": 0.0
            },
            "combined": {
                "50th": 1.0,
                "90th": 3.0,
                "95th": 3.0,
                "100th": 45.0
            }
        }
    },
    {
        "processed_items": 60000,
        "avg_error": 1.236321483771252,
        "overestimation_percentage": 72.73570324574962,
        "underestimation_percentage": 0.0,
        "exact_match_percentage": 27.26429675425039,
        "avg_query_time": 3.6780834197998046e-06,
        "memory_usage": 48000.0,
        "load_factor": 0.9625,
        "percentiles": {
            "overestimation": {
                "50th": 1.0,
                "90th": 3.0,
                "95th": 3.0,
                "100th": 47.0
            },
            "underestimation": {
                "50th": 0.0,
                "90th": 0.0,
                "95th": 0.0,
                "100th": 0.0
            },
            "combined": {
                "50th": 1.0,
                "90th": 3.0,
                "95th": 3.0,
                "100th": 47.0
            }
        }
    },
    {
        "processed_items": 62000,
        "avg_error": 1.2942677070828332,
        "overestimation_percentage": 74.53481392557023,
        "underestimation_percentage": 0.0,
        "exact_match_percentage": 25.465186074429774,
        "avg_query_time": 3.5829544067382814e-06,
        "memory_usage": 48000.0,
        "load_factor": 0.965,
        "percentiles": {
            "overestimation": {
                "50th": 1.0,
                "90th": 3.0,
                "95th": 3.0,
                "100th": 48.0
            },
            "underestimation": {
                "50th": 0.0,
                "90th": 0.0,
                "95th": 0.0,
                "100th": 0.0
            },
            "combined": {
                "50th": 1.0,
                "90th": 3.0,
                "95th": 3.0,
                "100th": 48.0
            }
        }
    },
    {
        "processed_items": 64000,
        "avg_error": 1.34580948187289,
        "overestimation_percentage": 75.50271539703508,
        "underestimation_percentage": 0.0,
        "exact_match_percentage": 24.497284602964918,
        "avg_query_time": 3.7577152252197264e-06,
        "memory_usage": 48000.0,
        "load_factor": 0.9685,
        "percentiles": {
            "overestimation": {
                "50th": 2.0,
                "90th": 3.0,
                "95th": 3.0,
                "100th": 48.0
            },
            "underestimation": {
                "50th": 0.0,
                "90th": 0.0,
                "95th": 0.0,
                "100th": 0.0
            },
            "combined": {
                "50th": 2.0,
                "90th": 3.0,
                "95th": 3.0,
                "100th": 48.0
            }
        }
    },
    {
        "processed_items": 66000,
        "avg_error": 1.4065052299756413,
        "overestimation_percentage": 76.84482017481015,
        "underestimation_percentage": 0.0,
        "exact_match_percentage": 23.155179825189855,
        "avg_query_time": 3.602743148803711e-06,
        "memory_usage": 48000.0,
        "load_factor": 0.9715,
        "percentiles": {
            "overestimation": {
                "50th": 2.0,
                "90th": 3.0,
                "95th": 3.0,
                "100th": 51.0
            },
            "underestimation": {
                "50th": 0.0,
                "90th": 0.0,
                "95th": 0.0,
                "100th": 0.0
            },
            "combined": {
                "50th": 2.0,
                "90th": 3.0,
                "95th": 3.0,
                "100th": 51.0
            }
        }
    },
    {
        "processed_items": 68000,
        "avg_error": 1.4649208794286515,
        "overestimation_percentage": 78.15432012323204,
        "underestimation_percentage": 0.0,
        "exact_match_percentage": 21.84567987676796,
        "avg_query_time": 3.628969192504883e-06,
        "memory_usage": 48000.0,
        "load_factor": 0.9735,
        "percentiles": {
            "overestimation": {
                "50th": 2.0,
                "90th": 3.0,
                "95th": 4.0,
                "100th": 52.0
            },
            "underestimation": {
                "50th": 0.0,
                "90th": 0.0,
                "95th": 0.0,
                "100th": 0.0
            },
            "combined": {
                "50th": 2.0,
                "90th": 3.0,
                "95th": 4.0,
                "100th": 52.0
            }
        }
    },
    {
        "processed_items": 70000,
        "avg_error": 1.5216796607851184,
        "overestimation_percentage": 79.38722472985911,
        "underestimation_percentage": 0.0,
        "exact_match_percentage": 20.612775270140883,
        "avg_query_time": 4.170894622802734e-06,
        "memory_usage": 48000.0,
        "load_factor": 0.976,
        "percentiles": {
            "overestimation": {
                "50th": 2.0,
                "90th": 3.0,
                "95th": 4.0,
                "100th": 54.0
            },
            "underestimation": {
                "50th": 0.0,
                "90th": 0.0,
                "95th": 0.0,
                "100th": 0.0
            },
            "combined": {
                "50th": 2.0,
                "90th": 3.0,
                "95th": 4.0,
                "100th": 54.0
            }
        }
    },
    {
        "processed_items": 72000,
        "avg_error": 1.572480256993709,
        "overestimation_percentage": 80.47115513318164,
        "underestimation_percentage": 0.0,
        "exact_match_percentage": 19.528844866818364,
        "avg_query_time": 3.6132335662841795e-06,
        "memory_usage": 48000.0,
        "load_factor": 0.978,
        "percentiles": {
            "overestimation": {
                "50th": 2.0,
                "90th": 3.0,
                "95th": 4.0,
                "100th": 55.0
            },
            "underestimation": {
                "50th": 0.0,
                "90th": 0.0,
                "95th": 0.0,
                "100th": 0.0
            },
            "combined": {
                "50th": 2.0,
                "90th": 3.0,
                "95th": 4.0,
                "100th": 55.0
            }
        }
    },
    {
        "processed_items": 74000,
        "avg_error": 1.6262785208497246,
        "overestimation_percentage": 81.43194335169159,
        "underestimation_percentage": 0.0,
        "exact_match_percentage": 18.568056648308417,
        "avg_query_time": 3.6590099334716796e-06,
        "memory_usage": 48000.0,
        "load_factor": 0.9795,
        "percentiles": {
            "overestimation": {
                "50th": 2.0,
                "90th": 3.0,
                "95th": 4.0,
                "100th": 57.0
            },
            "underestimation": {
                "50th": 0.0,
                "90th": 0.0,
                "95th": 0.0,
                "100th": 0.0
            },
            "combined": {
                "50th": 2.0,
                "90th": 3.0,
                "95th": 4.0,
                "100th": 57.0
            }
        }
    },
    {
        "processed_items": 76000,
        "avg_error": 1.688965782391388,
        "overestimation_percentage": 82.3913879277201,
        "underestimation_percentage": 0.0,
        "exact_match_percentage": 17.608612072279893,
        "avg_query_time": 3.607034683227539e-06,
        "memory_usage": 48000.0,
        "load_factor": 0.982,
        "percentiles": {
            "overestimation": {
                "50th": 2.0,
                "90th": 3.0,
                "95th": 4.0,
                "100th": 61.0
            },
            "underestimation": {
                "50th": 0.0,
                "90th": 0.0,
                "95th": 0.0,
                "100th": 0.0
            },
            "combined": {
                "50th": 2.0,
                "90th": 3.0,
                "95th": 4.0,
                "100th": 61.0
            }
        }
    },
    {
        "processed_items": 78000,
        "avg_error": 1.7449799196787148,
        "overestimation_percentage": 83.17018072289156,
        "underestimation_percentage": 0.0,
        "exact_match_percentage": 16.829819277108435,
        "avg_query_time": 3.5250186920166016e-06,
        "memory_usage": 48000.0,
        "load_factor": 0.984,
        "percentiles": {
            "overestimation": {
                "50th": 2.0,
                "90th": 3.0,
                "95th": 4.0,
                "100th": 61.0
            },
            "underestimation": {
                "50th": 0.0,
                "90th": 0.0,
                "95th": 0.0,
                "100th": 0.0
            },
            "combined": {
                "50th": 2.0,
                "90th": 3.0,
                "95th": 4.0,
                "100th": 61.0
            }
        }
    },
    {
        "processed_items": 80000,
        "avg_error": 1.803268616367658,
        "overestimation_percentage": 83.9641189481445,
        "underestimation_percentage": 0.0,
        "exact_match_percentage": 16.035881051855494,
        "avg_query_time": 4.202127456665039e-06,
        "memory_usage": 48000.0,
        "load_factor": 0.9865,
        "percentiles": {
            "overestimation": {
                "50th": 2.0,
                "90th": 3.0,
                "95th": 4.0,
                "100th": 62.0
            },
            "underestimation": {
                "50th": 0.0,
                "90th": 0.0,
                "95th": 0.0,
                "100th": 0.0
            },
            "combined": {
                "50th": 2.0,
                "90th": 3.0,
                "95th": 4.0,
                "100th": 62.0
            }
        }
    },
    {
        "processed_items": 82000,
        "avg_error": 1.859985528219971,
        "overestimation_percentage": 84.70815243608297,
        "underestimation_percentage": 0.0,
        "exact_match_percentage": 15.29184756391703,
        "avg_query_time": 3.6001205444335937e-06,
        "memory_usage": 48000.0,
        "load_factor": 0.9875,
        "percentiles": {
            "overestimation": {
                "50th": 2.0,
                "90th": 3.0,
                "95th": 4.0,
                "100th": 64.0
            },
            "underestimation": {
                "50th": 0.0,
                "90th": 0.0,
                "95th": 0.0,
                "100th": 0.0
            },
            "combined": {
                "50th": 2.0,
                "90th": 3.0,
                "95th": 4.0,
                "100th": 64.0
            }
        }
    },
    {
        "processed_items": 84000,
        "avg_error": 1.9121974371143806,
        "overestimation_percentage": 85.46511627906976,
        "underestimation_percentage": 0.0,
        "exact_match_percentage": 14.534883720930234,
        "avg_query_time": 3.5941600799560545e-06,
        "memory_usage": 48000.0,
        "load_factor": 0.988,
        "percentiles": {
            "overestimation": {
                "50th": 2.0,
                "90th": 4.0,
                "95th": 4.0,
                "100th": 64.0
            },
            "underestimation": {
                "50th": 0.0,
                "90th": 0.0,
                "95th": 0.0,
                "100th": 0.0
            },
            "combined": {
                "50th": 2.0,
                "90th": 4.0,
                "95th": 4.0,
                "100th": 64.0
            }
        }
    },
    {
        "processed_items": 86000,
        "avg_error": 1.9794943492951182,
        "overestimation_percentage": 86.0188745193988,
        "underestimation_percentage": 0.0,
        "exact_match_percentage": 13.98112548060119,
        "avg_query_time": 3.591775894165039e-06,
        "memory_usage": 48000.0,
        "load_factor": 0.9895,
        "percentiles": {
            "overestimation": {
                "50th": 2.0,
                "90th": 4.0,
                "95th": 4.0,
                "100th": 64.0
            },
            "underestimation": {
                "50th": 0.0,
                "90th": 0.0,
                "95th": 0.0,
                "100th": 0.0
            },
            "combined": {
                "50th": 2.0,
                "90th": 4.0,
                "95th": 4.0,
                "100th": 64.0
            }
        }
    },
    {
        "processed_items": 88000,
        "avg_error": 2.0337876531897834,
        "overestimation_percentage": 86.67964723399382,
        "underestimation_percentage": 0.0,
        "exact_match_percentage": 13.320352766006186,
        "avg_query_time": 3.607034683227539e-06,
        "memory_usage": 48000.0,
        "load_factor": 0.99,
        "percentiles": {
            "overestimation": {
                "50th": 2.0,
                "90th": 4.0,
                "95th": 4.0,
                "100th": 65.0
            },
            "underestimation": {
                "50th": 0.0,
                "90th": 0.0,
                "95th": 0.0,
                "100th": 0.0
            },
            "combined": {
                "50th": 2.0,
                "90th": 4.0,
                "95th": 4.0,
                "100th": 65.0
            }
        }
    },
    {
        "processed_items": 90000,
        "avg_error": 2.091431145141313,
        "overestimation_percentage": 87.15234770859138,
        "underestimation_percentage": 0.0,
        "exact_match_percentage": 12.847652291408625,
        "avg_query_time": 3.6380290985107423e-06,
        "memory_usage": 48000.0,
        "load_factor": 0.991,
        "percentiles": {
            "overestimation": {
                "50th": 2.0,
                "90th": 4.0,
                "95th": 4.049999999999272,
                "100th": 67.0
            },
            "underestimation": {
                "50th": 0.0,
                "90th": 0.0,
                "95th": 0.0,
                "100th": 0.0
            },
            "combined": {
                "50th": 2.0,
                "90th": 4.0,
                "95th": 4.049999999999272,
                "100th": 67.0
            }
        }
    },
    {
        "processed_items": 92000,
        "avg_error": 2.1453841901603097,
        "overestimation_percentage": 87.7501381978994,
        "underestimation_percentage": 0.0,
        "exact_match_percentage": 12.249861802100607,
        "avg_query_time": 3.7078857421875e-06,
        "memory_usage": 48000.0,
        "load_factor": 0.992,
        "percentiles": {
            "overestimation": {
                "50th": 2.0,
                "90th": 4.0,
                "95th": 5.0,
                "100th": 68.0
            },
            "underestimation": {
                "50th": 0.0,
                "90th": 0.0,
                "95th": 0.0,
                "100th": 0.0
            },
            "combined": {
                "50th": 2.0,
                "90th": 4.0,
                "95th": 5.0,
                "100th": 68.0
            }
        }
    },
    {
        "processed_items": 94000,
        "avg_error": 2.2003478638982497,
        "overestimation_percentage": 88.46613762365475,
        "underestimation_percentage": 0.0,
        "exact_match_percentage": 11.533862376345255,
        "avg_query_time": 3.5848617553710937e-06,
        "memory_usage": 48000.0,
        "load_factor": 0.992,
        "percentiles": {
            "overestimation": {
                "50th": 2.0,
                "90th": 4.0,
                "95th": 5.0,
                "100th": 69.0
            },
            "underestimation": {
                "50th": 0.0,
                "90th": 0.0,
                "95th": 0.0,
                "100th": 0.0
            },
            "combined": {
                "50th": 2.0,
                "90th": 4.0,
                "95th": 5.0,
                "100th": 69.0
            }
        }
    },
    {
        "processed_items": 96000,
        "avg_error": 2.255779109589041,
        "overestimation_percentage": 88.84845890410958,
        "underestimation_percentage": 0.0,
        "exact_match_percentage": 11.15154109589041,
        "avg_query_time": 3.592014312744141e-06,
        "memory_usage": 48000.0,
        "load_factor": 0.992,
        "percentiles": {
            "overestimation": {
                "50th": 2.0,
                "90th": 4.0,
                "95th": 5.0,
                "100th": 69.0
            },
            "underestimation": {
                "50th": 0.0,
                "90th": 0.0,
                "95th": 0.0,
                "100th": 0.0
            },
            "combined": {
                "50th": 2.0,
                "90th": 4.0,
                "95th": 5.0,
                "100th": 69.0
            }
        }
    },
    {
        "processed_items": 98000,
        "avg_error": 2.3027871621621623,
        "overestimation_percentage": 89.21030405405406,
        "underestimation_percentage": 0.0,
        "exact_match_percentage": 10.789695945945946,
        "avg_query_time": 3.588199615478516e-06,
        "memory_usage": 48000.0,
        "load_factor": 0.993,
        "percentiles": {
            "overestimation": {
                "50th": 2.0,
                "90th": 4.0,
                "95th": 5.0,
                "100th": 69.0
            },
            "underestimation": {
                "50th": 0.0,
                "90th": 0.0,
                "95th": 0.0,
                "100th": 0.0
            },
            "combined": {
                "50th": 2.0,
                "90th": 4.0,
                "95th": 5.0,
                "100th": 69.0
            }
        }
    },
    {
        "processed_items": 100000,
        "avg_error": 2.361934477379095,
        "overestimation_percentage": 89.50598023920958,
        "underestimation_percentage": 0.0,
        "exact_match_percentage": 10.494019760790433,
        "avg_query_time": 3.552913665771484e-06,
        "memory_usage": 48000.0,
        "load_factor": 0.995,
        "percentiles": {
            "overestimation": {
                "50th": 2.0,
                "90th": 4.0,
                "95th": 5.0,
                "100th": 73.0
            },
            "underestimation": {
                "50th": 0.0,
                "90th": 0.0,
                "95th": 0.0,
                "100th": 0.0
            },
            "combined": {
                "50th": 2.0,
                "90th": 4.0,
                "95th": 5.0,
                "100th": 73.0
            }
        }
    },
    {
        "processed_items": 102000,
        "avg_error": 2.4213707611925006,
        "overestimation_percentage": 89.87808626165352,
        "underestimation_percentage": 0.0,
        "exact_match_percentage": 10.12191373834648,
        "avg_query_time": 3.598928451538086e-06,
        "memory_usage": 48000.0,
        "load_factor": 0.995,
        "percentiles": {
            "overestimation": {
                "50th": 2.0,
                "90th": 4.0,
                "95th": 5.0,
                "100th": 74.0
            },
            "underestimation": {
                "50th": 0.0,
                "90th": 0.0,
                "95th": 0.0,
                "100th": 0.0
            },
            "combined": {
                "50th": 2.0,
                "90th": 4.0,
                "95th": 5.0,
                "100th": 74.0
            }
        }
    }
]